pytest_auto_fixture/__init__.py
pytest_auto_fixture/plugin.py
pytest_auto_fixture-0.1.0.dist-info/LICENSE.txt
pytest_auto_fixture-0.1.0.dist-info/METADATA
pytest_auto_fixture-0.1.0.dist-info/WHEEL
pytest_auto_fixture-0.1.0.dist-info/entry_points.txt
pytest_auto_fixture-0.1.0.dist-info/top_level.txt
pytest_auto_fixture-0.1.0.dist-info/RECORD
