Metadata-Version: 2.1
Name: pytest-auto-fixture
Version: 0.1.0
Summary: ...
Author: Daniel Pepper
License: The MIT License (MIT)
Project-URL: Homepage, https://github.com/dpep/pytest-auto-fixture
Classifier: Framework :: Pytest
Classifier: License :: OSI Approved :: MIT License
Classifier: Topic :: Software Development :: Testing
Requires-Python: >=3
License-File: LICENSE.txt
Requires-Dist: pytest >=8
Provides-Extra: test
Requires-Dist: isort >=5.13 ; extra == 'test'
